ipconv/__init__.py
ipconv/ipconv.py
ipconv-0.0.4.dist-info/METADATA
ipconv-0.0.4.dist-info/RECORD
ipconv-0.0.4.dist-info/WHEEL
ipconv-0.0.4.dist-info/top_level.txt
