Metadata-Version: 2.1
Name: ipconv
Version: 0.0.4
Summary: An easy and convenient IP address operation library
Home-page: https://github.com/Cartmanishere/IPLib
Author: Pranav Gajjewar
Author-email: apbetahouse45@gmail.com
License: UNKNOWN
Platform: UNKNOWN
Classifier: Programming Language :: Python :: 3
Classifier: License :: OSI Approved :: MIT License
Classifier: Operating System :: OS Independent
